[
    {
        "id": "480536623198357",
        "panorama": "480536623198357.jpg",
        "gps": [
            19.938101,
            50.062275
        ],
        "sphereCorrection": {
            "pan": 38.329912025392
        }
    },
    {
        "id": "253554073121816",
        "panorama": "253554073121816.jpg",
        "gps": [
            19.939330224404,
            50.061406639629
        ],
        "sphereCorrection": {
            "pan": 117.26247630313
        }
    },
    {
        "id": "486602376090306",
        "panorama": "486602376090306.jpg",
        "gps": [
            19.940233,
            50.060833
        ],
        "sphereCorrection": {
            "pan": 0
        }
    },
    {
        "id": "764609671083851",
        "panorama": "764609671083851.jpg",
        "gps": [
            19.937508699975,
            50.06100287997
        ],
        "sphereCorrection": {
            "pan": 352.65041789174
        }
    },
    {
        "id": "870538127137671",
        "panorama": "870538127137671.jpg",
        "gps": [
            19.937763,
            50.061539000082
        ],
        "sphereCorrection": {
            "pan": 304.05236539162
        }
    },
    {
        "id": "292831848989209",
        "panorama": "292831848989209.jpg",
        "gps": [
            19.937706,
            50.060741000104
        ],
        "sphereCorrection": {
            "pan": 219.36609475886
        }
    },
    {
        "id": "466511391075918",
        "panorama": "466511391075918.jpg",
        "gps": [
            19.939827,
            50.061508
        ],
        "sphereCorrection": {
            "pan": 0
        }
    },
    {
        "id": "192177549404062",
        "panorama": "192177549404062.jpg",
        "gps": [
            19.93964,
            50.061947000079
        ],
        "sphereCorrection": {
            "pan": 0
        }
    },
    {
        "id": "2556122138016746",
        "panorama": "2556122138016746.jpg",
        "gps": [
            19.937496,
            50.062416
        ],
        "sphereCorrection": {
            "pan": 194.15000586999
        }
    },
    {
        "id": "832068457667596",
        "panorama": "832068457667596.jpg",
        "gps": [
            19.94018,
            50.061649
        ],
        "sphereCorrection": {
            "pan": 2.6070687927554
        }
    },
    {
        "id": "786955041962719",
        "panorama": "786955041962719.jpg",
        "gps": [
            19.938305,
            50.062313
        ],
        "sphereCorrection": {
            "pan": 350.45283760583
        }
    },
    {
        "id": "297917758597860",
        "panorama": "297917758597860.jpg",
        "gps": [
            19.938201,
            50.0618325
        ],
        "sphereCorrection": {
            "pan": 180.99902750035
        }
    },
    {
        "id": "886604912012029",
        "panorama": "886604912012029.jpg",
        "gps": [
            19.935736,
            50.062294
        ],
        "sphereCorrection": {
            "pan": 23.860602975713
        }
    },
    {
        "id": "860214887860579",
        "panorama": "860214887860579.jpg",
        "gps": [
            19.936172,
            50.062149
        ],
        "sphereCorrection": {
            "pan": 293.50114204635
        }
    },
    {
        "id": "1474823546189994",
        "panorama": "1474823546189994.jpg",
        "gps": [
            19.938038,
            50.062126
        ],
        "sphereCorrection": {
            "pan": 65.574663761148
        }
    },
    {
        "id": "457115142216255",
        "panorama": "457115142216255.jpg",
        "gps": [
            19.938343,
            50.062176
        ],
        "sphereCorrection": {
            "pan": 160.37790758977
        }
    },
    {
        "id": "304759761032419",
        "panorama": "304759761032419.jpg",
        "gps": [
            19.937206,
            50.061047
        ],
        "sphereCorrection": {
            "pan": 285.38334450922
        }
    },
    {
        "id": "2825105044411441",
        "panorama": "2825105044411441.jpg",
        "gps": [
            19.940092,
            50.061855
        ],
        "sphereCorrection": {
            "pan": 6.8301138968162
        }
    },
    {
        "id": "217910133427739",
        "panorama": "217910133427739.jpg",
        "gps": [
            19.9361325,
            50.06176549998
        ],
        "sphereCorrection": {
            "pan": 316.71365673834
        }
    },
    {
        "id": "807797359863981",
        "panorama": "807797359863981.jpg",
        "gps": [
            19.938589,
            50.062183
        ],
        "sphereCorrection": {
            "pan": 237.45962808697
        }
    },
    {
        "id": "503365164033454",
        "panorama": "503365164033454.jpg",
        "gps": [
            19.936728,
            50.061176
        ],
        "sphereCorrection": {
            "pan": 311.17404802269
        }
    },
    {
        "id": "294755352295048",
        "panorama": "294755352295048.jpg",
        "gps": [
            19.939098,
            50.062073
        ],
        "sphereCorrection": {
            "pan": 320.92442268379
        }
    },
    {
        "id": "963367924493058",
        "panorama": "963367924493058.jpg",
        "gps": [
            19.9386825,
            50.062054499961
        ],
        "sphereCorrection": {
            "pan": 137.78316688044
        }
    },
    {
        "id": "214767020081327",
        "panorama": "214767020081327.jpg",
        "gps": [
            19.93755698,
            50.061070029947
        ],
        "sphereCorrection": {
            "pan": 287.75438094419
        }
    },
    {
        "id": "857754728106343",
        "panorama": "857754728106343.jpg",
        "gps": [
            19.938943983185,
            50.061458296944
        ],
        "sphereCorrection": {
            "pan": 71.75577389964
        }
    },
    {
        "id": "371117170884756",
        "panorama": "371117170884756.jpg",
        "gps": [
            19.9375,
            50.062546
        ],
        "sphereCorrection": {
            "pan": 331.23174490118
        }
    },
    {
        "id": "821451488465066",
        "panorama": "821451488465066.jpg",
        "gps": [
            19.936159,
            50.061333
        ],
        "sphereCorrection": {
            "pan": 51.964289519076
        }
    },
    {
        "id": "527366731958521",
        "panorama": "527366731958521.jpg",
        "gps": [
            19.938498333333,
            50.061487666667
        ],
        "sphereCorrection": {
            "pan": 277.88014573605
        }
    },
    {
        "id": "484626606147004",
        "panorama": "484626606147004.jpg",
        "gps": [
            19.938187,
            50.060364
        ],
        "sphereCorrection": {
            "pan": 188.92203085543
        }
    },
    {
        "id": "3671940096268143",
        "panorama": "3671940096268143.jpg",
        "gps": [
            19.934933,
            50.062592
        ],
        "sphereCorrection": {
            "pan": 282.25852615843
        }
    },
    {
        "id": "164095525622425",
        "panorama": "164095525622425.jpg",
        "gps": [
            19.935846,
            50.061459
        ],
        "sphereCorrection": {
            "pan": 223.8279413625
        }
    },
    {
        "id": "295016908993298",
        "panorama": "295016908993298.jpg",
        "gps": [
            19.93816,
            50.061131
        ],
        "sphereCorrection": {
            "pan": 217.51007806591
        }
    },
    {
        "id": "373622010627023",
        "panorama": "373622010627023.jpg",
        "gps": [
            19.937725,
            50.060444
        ],
        "sphereCorrection": {
            "pan": 234.71825791108
        }
    }
]